keenmqtt
