Metadata-Version: 1.1
Name: keenmqtt
Version: 0.0.9
Summary: An MQTT client which will send configured MQTT messages to keen IO as events for later analysis.
Home-page: https://github.com/ZoetropeImaging/keenmqtt
Author: Ben Howes
Author-email: ben@zoetrope.io
License: MIT
Platform: any
Classifier: Programming Language :: Python
Classifier: Natural Language :: English
Classifier: Intended Audience :: Developers
Classifier: License :: OSI Approved :: MIT License
Classifier: Operating System :: OS Independent
Classifier: Topic :: Software Development :: Libraries :: Python Modules
